README.md
setup.py
libpytools/__init__.py
libpytools/github_api.py
pytoolsc2.egg-info/PKG-INFO
pytoolsc2.egg-info/SOURCES.txt
pytoolsc2.egg-info/dependency_links.txt
pytoolsc2.egg-info/not-zip-safe
pytoolsc2.egg-info/requires.txt
pytoolsc2.egg-info/top_level.txt